{
  "lastScraped": 1779464976509,
  "posts": [],
  "comments": [],
  "tweets": [
    {
      "id": "x_2057851033481568612",
      "text": "@TomPark1n Well it's safe to say like everyone else, Brad Bradford thinks Brad Bradford is incompetent. And he's right.",
      "author": "John Rathiganthan - City of Heresy arc",
      "handle": "@JRathiganthan",
      "likes": 0,
      "retweets": 0,
      "created_utc": 1779464894,
      "permalink": "https://x.com/JRathiganthan/status/2057851033481568612",
      "source": "twitter"
    },
    {
      "id": "x_2057850920411472161",
      "text": "RT @observinthecity: Brad Bradford on his way to literally rain on our parade. Remember this when he shows up during pride trying to pander…",
      "author": "fun facts with lulu 🌈 😷",
      "handle": "@FunFactsLulu",
      "likes": 0,
      "retweets": 13,
      "created_utc": 1779464867,
      "permalink": "https://x.com/FunFactsLulu/status/2057850920411472161",
      "source": "twitter"
    },
    {
      "id": "x_2057850695844331951",
      "text": "RT @3mpwrApp0816: 🔥 Injured Workers Day 2026\n\n• Thunder Bay: May 29, 10 AM (City Hall)\n\n• Toronto: June 1, 11 AM (Queens Park)\n\n• Hamilton:…",
      "author": "JMAK FrYrEyesOnly@yahoo.com",
      "handle": "@JenFrYrEyesOnly",
      "likes": 0,
      "retweets": 7,
      "created_utc": 1779464813,
      "permalink": "https://x.com/JenFrYrEyesOnly/status/2057850695844331951",
      "source": "twitter"
    },
    {
      "id": "x_2057850534993031342",
      "text": "RT @AKAfeng37: Toronto, is your bank in bed with the Chinese Communist Party? Your mayor is!\n\nLast year we brought you the GTA bank VP who…",
      "author": "Found in Translation 🇨🇦🇺🇦🇺🇲",
      "handle": "@BlueBellsForest",
      "likes": 0,
      "retweets": 4,
      "created_utc": 1779464775,
      "permalink": "https://x.com/BlueBellsForest/status/2057850534993031342",
      "source": "twitter"
    },
    {
      "id": "x_2057849736682484062",
      "text": "RT @mario4thenorth: BREAKING: Olivia Chow just threatened to raise property taxes in Toronto if the federal government doesn’t give her mor…",
      "author": "Northernlights",
      "handle": "@qyz808kglu",
      "likes": 0,
      "retweets": 960,
      "created_utc": 1779464584,
      "permalink": "https://x.com/qyz808kglu/status/2057849736682484062",
      "source": "twitter"
    },
    {
      "id": "x_2057849627328618578",
      "text": "RT @Great_Cdn_Moose: Olivia Chow, thought it would be a great idea to spend $200,000 of taxpayers money for half 1 million FIFA branded con…",
      "author": "Northernlights",
      "handle": "@qyz808kglu",
      "likes": 0,
      "retweets": 5,
      "created_utc": 1779464558,
      "permalink": "https://x.com/qyz808kglu/status/2057849627328618578",
      "source": "twitter"
    },
    {
      "id": "x_2057849487607919015",
      "text": "RT @MarcNixon24: The Blue Jays lost the World Series.\n\nOlivia Chow made sure fans lost their ride home too.\n\nNo subways after the game. Ten…",
      "author": "Northernlights",
      "handle": "@qyz808kglu",
      "likes": 0,
      "retweets": 2032,
      "created_utc": 1779464525,
      "permalink": "https://x.com/qyz808kglu/status/2057849487607919015",
      "source": "twitter"
    },
    {
      "id": "x_2057849421883134188",
      "text": "RT @edwardrow: Brad Bradford voted against the city seeking actions to curb motorcycle style e-bikes and scooters on sidewalks in December…",
      "author": "Sandra Quinn",
      "handle": "@SandraQ26411803",
      "likes": 0,
      "retweets": 107,
      "created_utc": 1779464509,
      "permalink": "https://x.com/SandraQ26411803/status/2057849421883134188",
      "source": "twitter"
    },
    {
      "id": "x_2057848839055261931",
      "text": "RT @Kurrco: Toronto Mayor Olivia Chow is embracing the “Crolivia” nickname Drake gave her in a thank-you note 😭\n\n\"What do you mean you didn…",
      "author": "BigBaale 🫰🏾",
      "handle": "@bigbaale375",
      "likes": 0,
      "retweets": 193,
      "created_utc": 1779464370,
      "permalink": "https://x.com/bigbaale375/status/2057848839055261931",
      "source": "twitter"
    },
    {
      "id": "x_2057848505775817013",
      "text": "RT @Kurrco: Toronto Mayor Olivia Chow is embracing the “Crolivia” nickname Drake gave her in a thank-you note 😭\n\n\"What do you mean you didn…",
      "author": "Rickey Steamboat 🐉",
      "handle": "@NickAtNit333",
      "likes": 0,
      "retweets": 193,
      "created_utc": 1779464291,
      "permalink": "https://x.com/NickAtNit333/status/2057848505775817013",
      "source": "twitter"
    },
    {
      "id": "x_2057848117966328035",
      "text": "@PJforTO Olivia chow no longer uses orange but municipal NDP colour is purple now https://t.co/UnOUsrDOFW",
      "author": "George Sawision ME",
      "handle": "@GSawision",
      "likes": 0,
      "retweets": 0,
      "created_utc": 1779464198,
      "permalink": "https://x.com/GSawision/status/2057848117966328035",
      "source": "twitter"
    },
    {
      "id": "x_2057848080750322150",
      "text": "RT @RTNToronto: Toronto Mayor Olivia Chow reads her mean comments! 😭 https://t.co/FjJyBnN0x9",
      "author": "Northernlights",
      "handle": "@qyz808kglu",
      "likes": 0,
      "retweets": 5,
      "created_utc": 1779464190,
      "permalink": "https://x.com/qyz808kglu/status/2057848080750322150",
      "source": "twitter"
    },
    {
      "id": "x_2057847547327103271",
      "text": "RT @Kurrco: Toronto Mayor Olivia Chow is embracing the “Crolivia” nickname Drake gave her in a thank-you note 😭\n\n\"What do you mean you didn…",
      "author": "emma smith",
      "handle": "@emmasmith9906",
      "likes": 0,
      "retweets": 193,
      "created_utc": 1779464062,
      "permalink": "https://x.com/emmasmith9906/status/2057847547327103271",
      "source": "twitter"
    },
    {
      "id": "x_2057847188089164215",
      "text": "RT @db_maggi: @imPatrickT The Cinesphere at Ontario Place in Toronto, was the world’s first permanent IMAX cinema until City Hall and Doug…",
      "author": "Genevieve Walker",
      "handle": "@talkmoviestome0",
      "likes": 0,
      "retweets": 2,
      "created_utc": 1779463977,
      "permalink": "https://x.com/talkmoviestome0/status/2057847188089164215",
      "source": "twitter"
    },
    {
      "id": "x_2057846671585788366",
      "text": "@PJforTO Start with Ford perks,Paula fletcher,Olivia chow, then the fake liberals like Shelley Carrol and others forms a political majority https://t.co/cJ4JD2uFZu",
      "author": "George Sawision ME",
      "handle": "@GSawision",
      "likes": 0,
      "retweets": 0,
      "created_utc": 1779463854,
      "permalink": "https://x.com/GSawision/status/2057846671585788366",
      "source": "twitter"
    },
    {
      "id": "x_2057846225160770047",
      "text": "RT @Kurrco: Toronto Mayor Olivia Chow is embracing the “Crolivia” nickname Drake gave her in a thank-you note 😭\n\n\"What do you mean you didn…",
      "author": "TheMuffinMan",
      "handle": "@leleybriann",
      "likes": 0,
      "retweets": 193,
      "created_utc": 1779463747,
      "permalink": "https://x.com/leleybriann/status/2057846225160770047",
      "source": "twitter"
    },
    {
      "id": "x_2057845503765737657",
      "text": "RT @Kurrco: Toronto Mayor Olivia Chow is embracing the “Crolivia” nickname Drake gave her in a thank-you note 😭\n\n\"What do you mean you didn…",
      "author": "bejdojeji🦉",
      "handle": "@sybgdhud",
      "likes": 0,
      "retweets": 193,
      "created_utc": 1779463575,
      "permalink": "https://x.com/sybgdhud/status/2057845503765737657",
      "source": "twitter"
    },
    {
      "id": "x_2057845326208455107",
      "text": "RT @Kurrco: Toronto Mayor Olivia Chow is embracing the “Crolivia” nickname Drake gave her in a thank-you note 😭\n\n\"What do you mean you didn…",
      "author": "Troy",
      "handle": "@stephbeballin",
      "likes": 0,
      "retweets": 193,
      "created_utc": 1779463533,
      "permalink": "https://x.com/stephbeballin/status/2057845326208455107",
      "source": "twitter"
    },
    {
      "id": "x_2057844221168566737",
      "text": "RT @bowker_john: Art Eggleton: “As Toronto mayor, I supported the island airport. This is why I now oppose its expansion” https://t.co/TCWu…",
      "author": "bchiacchia",
      "handle": "@surphs__upp",
      "likes": 0,
      "retweets": 17,
      "created_utc": 1779463269,
      "permalink": "https://x.com/surphs__upp/status/2057844221168566737",
      "source": "twitter"
    },
    {
      "id": "x_2057844135843807241",
      "text": "RT @bowker_john: Art Eggleton: “As Toronto mayor, I supported the island airport. This is why I now oppose its expansion” https://t.co/TCWu…",
      "author": "LDF 🇨🇦",
      "handle": "@loisdelia",
      "likes": 0,
      "retweets": 17,
      "created_utc": 1779463249,
      "permalink": "https://x.com/loisdelia/status/2057844135843807241",
      "source": "twitter"
    },
    {
      "id": "x_2057842887400849607",
      "text": "RT @TomPark1n: Now that IntegrityTO has flamed out and won’t get free AM radio talk time to echo Brad Bradford, a new coalition of weirdos…",
      "author": "Miss Vida Boheme",
      "handle": "@L1bbychessler",
      "likes": 0,
      "retweets": 10,
      "created_utc": 1779462951,
      "permalink": "https://x.com/L1bbychessler/status/2057842887400849607",
      "source": "twitter"
    },
    {
      "id": "x_2057842733818040566",
      "text": "ABC Toronto (terrible name) is posting rage bait to get people to sign petitions, which they'll use to build an email list to elect Brad Bradford, who just happened to be onstage at their launch.",
      "author": "Aliya Pabani",
      "handle": "@aliyapabani",
      "likes": 3,
      "retweets": 0,
      "created_utc": 1779462915,
      "permalink": "https://x.com/aliyapabani/status/2057842733818040566",
      "source": "twitter"
    },
    {
      "id": "x_2057841205245829341",
      "text": "RT @TomPark1n: Now that IntegrityTO has flamed out and won’t get free AM radio talk time to echo Brad Bradford, a new coalition of weirdos…",
      "author": "Shirley Turnbull",
      "handle": "@TurnbullShirley",
      "likes": 0,
      "retweets": 10,
      "created_utc": 1779462550,
      "permalink": "https://x.com/TurnbullShirley/status/2057841205245829341",
      "source": "twitter"
    },
    {
      "id": "x_2057841049230356767",
      "text": "RT @mattybing: We're into silly season and it's worth noting that mayoral candidate Brad Bradford voted against a member's motion in Decemb…",
      "author": "Tiger Lilly",
      "handle": "@TOTigerLilly",
      "likes": 0,
      "retweets": 56,
      "created_utc": 1779462513,
      "permalink": "https://x.com/TOTigerLilly/status/2057841049230356767",
      "source": "twitter"
    },
    {
      "id": "x_2057840969764991175",
      "text": "RT @edwardrow: Brad Bradford voted against the city seeking actions to curb motorcycle style e-bikes and scooters on sidewalks in December…",
      "author": "JoeyGYYZ 🇨🇦",
      "handle": "@JoeyGYYZ",
      "likes": 0,
      "retweets": 107,
      "created_utc": 1779462494,
      "permalink": "https://x.com/JoeyGYYZ/status/2057840969764991175",
      "source": "twitter"
    },
    {
      "id": "x_2057839966449721775",
      "text": "@DokiroImaKaa @DschlopesIsBack @grok Olivia Chow, ‘widow’ of  Marxist/Socialist parasite Jack Layton, who was the leader of the Federal New Democratic Party in Canada.\n\nThis barely literate Marxist harridan is the current mayor of Toronto, Canada..",
      "author": "Doug Kenwright",
      "handle": "@Kursk1939",
      "likes": 0,
      "retweets": 0,
      "created_utc": 1779462255,
      "permalink": "https://x.com/Kursk1939/status/2057839966449721775",
      "source": "twitter"
    },
    {
      "id": "x_2057839566564811028",
      "text": "RT @TomPark1n: Now that IntegrityTO has flamed out and won’t get free AM radio talk time to echo Brad Bradford, a new coalition of weirdos…",
      "author": "JurassicJimmy",
      "handle": "@JurassicJimee",
      "likes": 0,
      "retweets": 10,
      "created_utc": 1779462160,
      "permalink": "https://x.com/JurassicJimee/status/2057839566564811028",
      "source": "twitter"
    },
    {
      "id": "x_2057839218131431902",
      "text": "RT @Kurrco: Toronto Mayor Olivia Chow is embracing the “Crolivia” nickname Drake gave her in a thank-you note 😭\n\n\"What do you mean you didn…",
      "author": "Mike🧊",
      "handle": "@m1keyd99",
      "likes": 0,
      "retweets": 193,
      "created_utc": 1779462077,
      "permalink": "https://x.com/m1keyd99/status/2057839218131431902",
      "source": "twitter"
    },
    {
      "id": "x_2057838211074773421",
      "text": "RT @AKAfeng37: Toronto, is your bank in bed with the Chinese Communist Party? Your mayor is!\n\nLast year we brought you the GTA bank VP who…",
      "author": "Lisa Massey",
      "handle": "@Lisamassey62",
      "likes": 0,
      "retweets": 4,
      "created_utc": 1779461836,
      "permalink": "https://x.com/Lisamassey62/status/2057838211074773421",
      "source": "twitter"
    },
    {
      "id": "x_2057838135942205640",
      "text": "RT @alexbrown17: Looking rough, Toronto.\n\nYou deserve a better class of councillor, mayor, premier…",
      "author": "Kenneth Cole",
      "handle": "@KennethCole24",
      "likes": 0,
      "retweets": 6,
      "created_utc": 1779461819,
      "permalink": "https://x.com/KennethCole24/status/2057838135942205640",
      "source": "twitter"
    },
    {
      "id": "x_2057837987430633726",
      "text": "RT @AKAfeng37: Toronto, is your bank in bed with the Chinese Communist Party? Your mayor is!\n\nLast year we brought you the GTA bank VP who…",
      "author": "Patricia🇨🇦",
      "handle": "@FixitCanada",
      "likes": 0,
      "retweets": 4,
      "created_utc": 1779461783,
      "permalink": "https://x.com/FixitCanada/status/2057837987430633726",
      "source": "twitter"
    },
    {
      "id": "x_2057837891284599206",
      "text": "RT @AkiHabte: The Toronto community celebrated the Flag raising event at City Hall today. Happy Eritrea Independence Day - 35th anniversary…",
      "author": "kemey.net",
      "handle": "@KemeyNet",
      "likes": 0,
      "retweets": 1,
      "created_utc": 1779461760,
      "permalink": "https://x.com/KemeyNet/status/2057837891284599206",
      "source": "twitter"
    },
    {
      "id": "x_2057837309530190174",
      "text": "RT @Kurrco: Toronto Mayor Olivia Chow is embracing the “Crolivia” nickname Drake gave her in a thank-you note 😭\n\n\"What do you mean you didn…",
      "author": "OVO letterman boyz 🧊",
      "handle": "@IceburgShortyy",
      "likes": 0,
      "retweets": 193,
      "created_utc": 1779461622,
      "permalink": "https://x.com/IceburgShortyy/status/2057837309530190174",
      "source": "twitter"
    },
    {
      "id": "x_2057836820524605710",
      "text": "RT @bowker_john: Art Eggleton: “As Toronto mayor, I supported the island airport. This is why I now oppose its expansion” https://t.co/TCWu…",
      "author": "Richard Julien",
      "handle": "@richardajulien",
      "likes": 0,
      "retweets": 17,
      "created_utc": 1779461505,
      "permalink": "https://x.com/richardajulien/status/2057836820524605710",
      "source": "twitter"
    },
    {
      "id": "x_2057836341635723364",
      "text": "RT @TomPark1n: Now that IntegrityTO has flamed out and won’t get free AM radio talk time to echo Brad Bradford, a new coalition of weirdos…",
      "author": "Alex Saint",
      "handle": "@SaintAlex1",
      "likes": 0,
      "retweets": 10,
      "created_utc": 1779461391,
      "permalink": "https://x.com/SaintAlex1/status/2057836341635723364",
      "source": "twitter"
    },
    {
      "id": "x_2057835482621300862",
      "text": "RT @TomPark1n: Now that IntegrityTO has flamed out and won’t get free AM radio talk time to echo Brad Bradford, a new coalition of weirdos…",
      "author": "Bruce",
      "handle": "@BrucewMitchell",
      "likes": 0,
      "retweets": 10,
      "created_utc": 1779461186,
      "permalink": "https://x.com/BrucewMitchell/status/2057835482621300862",
      "source": "twitter"
    },
    {
      "id": "x_2057834497417331190",
      "text": "RT @alexbrown17: Looking rough, Toronto.\n\nYou deserve a better class of councillor, mayor, premier…",
      "author": "J⏩",
      "handle": "@JcardinaJ",
      "likes": 0,
      "retweets": 6,
      "created_utc": 1779460951,
      "permalink": "https://x.com/JcardinaJ/status/2057834497417331190",
      "source": "twitter"
    },
    {
      "id": "x_2057833384747917635",
      "text": "RT @bowker_john: Art Eggleton: “As Toronto mayor, I supported the island airport. This is why I now oppose its expansion” https://t.co/TCWu…",
      "author": "charles vanvliet",
      "handle": "@cnqvv",
      "likes": 0,
      "retweets": 17,
      "created_utc": 1779460686,
      "permalink": "https://x.com/cnqvv/status/2057833384747917635",
      "source": "twitter"
    },
    {
      "id": "x_2057832800254914610",
      "text": "RT @bowker_john: Art Eggleton: “As Toronto mayor, I supported the island airport. This is why I now oppose its expansion” https://t.co/TCWu…",
      "author": "Bonnie",
      "handle": "@alandbonjones",
      "likes": 0,
      "retweets": 17,
      "created_utc": 1779460546,
      "permalink": "https://x.com/alandbonjones/status/2057832800254914610",
      "source": "twitter"
    },
    {
      "id": "x_2057832036702814680",
      "text": "@nenshi you got that olivia chow eye, you are fat and cannot speak properly,\n\nfuck off clown.",
      "author": "Sussyrua",
      "handle": "@sussyrua",
      "likes": 0,
      "retweets": 0,
      "created_utc": 1779460364,
      "permalink": "https://x.com/sussyrua/status/2057832036702814680",
      "source": "twitter"
    },
    {
      "id": "x_2057830128109920281",
      "text": "@ElectionDigest This is a disingenuous post\n\nYou completely forgot to mention that the issue is that this for a homeless shelter\n\nIt would be like saying Olivia Chow is anti science because she doesn’t want the Science Centre at Ontario Place\n\nBut we all know you’re a hack…",
      "author": "West End Robby",
      "handle": "@westendrobby",
      "likes": 0,
      "retweets": 0,
      "created_utc": 1779459909,
      "permalink": "https://x.com/westendrobby/status/2057830128109920281",
      "source": "twitter"
    },
    {
      "id": "x_2057830025320071606",
      "text": "@wokeshrekTO @abctoronto_ @KellyAizicowitz She's a flip flopper just like Brad Bradford",
      "author": "🌸K",
      "handle": "@K8844878198678",
      "likes": 1,
      "retweets": 0,
      "created_utc": 1779459885,
      "permalink": "https://x.com/K8844878198678/status/2057830025320071606",
      "source": "twitter"
    },
    {
      "id": "x_2057829317443289310",
      "text": "@observinthecity Brad Bradford is best buddies with Doug ford",
      "author": "🌸K",
      "handle": "@K8844878198678",
      "likes": 0,
      "retweets": 0,
      "created_utc": 1779459716,
      "permalink": "https://x.com/K8844878198678/status/2057829317443289310",
      "source": "twitter"
    },
    {
      "id": "x_2057828976169472032",
      "text": "RT @Kurrco: Toronto Mayor Olivia Chow is embracing the “Crolivia” nickname Drake gave her in a thank-you note 😭\n\n\"What do you mean you didn…",
      "author": "TheKomradeKenny",
      "handle": "@Thekomradekenny",
      "likes": 0,
      "retweets": 193,
      "created_utc": 1779459635,
      "permalink": "https://x.com/Thekomradekenny/status/2057828976169472032",
      "source": "twitter"
    },
    {
      "id": "x_2057828822934790637",
      "text": "RT @TomPark1n: Brad Bradford is running against Brad Bradford. Fun to watch.",
      "author": "Bretonponski",
      "handle": "@bretonpons17731",
      "likes": 0,
      "retweets": 2,
      "created_utc": 1779459598,
      "permalink": "https://x.com/bretonpons17731/status/2057828822934790637",
      "source": "twitter"
    },
    {
      "id": "x_2057825809663136065",
      "text": "Toronto Mayor Olivia Chow: We Need Media to Fight \"Homophobic Bullshit\"\n\nhttps://t.co/pEBYySJ0GM",
      "author": "Stigmabase | ORG",
      "handle": "@StigmabaseO",
      "likes": 0,
      "retweets": 0,
      "created_utc": 1779458880,
      "permalink": "https://x.com/StigmabaseO/status/2057825809663136065",
      "source": "twitter"
    },
    {
      "id": "x_2057825291355947364",
      "text": "RT @NightOwlsHQx: Toronto Mayor Olivia Chow is fully embracing the “Crolivia” nickname Drake gave her 😂\n\n“What do you mean you didn’t intro…",
      "author": "G ⁶𓅓🧊",
      "handle": "@OVOProballer",
      "likes": 0,
      "retweets": 14,
      "created_utc": 1779458756,
      "permalink": "https://x.com/OVOProballer/status/2057825291355947364",
      "source": "twitter"
    },
    {
      "id": "x_2057824242238885938",
      "text": "I may soon have to consider Brad Bradford's possible membership in my new political organization, Brads Against Brad Bradford. https://t.co/M8dwWtjh3f",
      "author": "Brad James",
      "handle": "@jamesbrad263",
      "likes": 0,
      "retweets": 0,
      "created_utc": 1779458506,
      "permalink": "https://x.com/jamesbrad263/status/2057824242238885938",
      "source": "twitter"
    },
    {
      "id": "x_2057822870340808789",
      "text": "@drivandalism \nHey Dean, you’re an idiot. Troll\n\nAll my fans, hope you’ll overwhelm this Brad Bradford supporter. https://t.co/roXCk4oHRO",
      "author": "The Truth about Brad Bradford.",
      "handle": "@TruthBrad29269",
      "likes": 1,
      "retweets": 0,
      "created_utc": 1779458179,
      "permalink": "https://x.com/TruthBrad29269/status/2057822870340808789",
      "source": "twitter"
    },
    {
      "id": "x_2057820338424025583",
      "text": "RT @TomPark1n: Now that IntegrityTO has flamed out and won’t get free AM radio talk time to echo Brad Bradford, a new coalition of weirdos…",
      "author": "Mark Gold 🟩",
      "handle": "@mj_gold",
      "likes": 0,
      "retweets": 10,
      "created_utc": 1779457575,
      "permalink": "https://x.com/mj_gold/status/2057820338424025583",
      "source": "twitter"
    },
    {
      "id": "x_2057820210481053896",
      "text": "RT @TomPark1n: Now that IntegrityTO has flamed out and won’t get free AM radio talk time to echo Brad Bradford, a new coalition of weirdos…",
      "author": "Election Digest",
      "handle": "@ElectionDigest",
      "likes": 0,
      "retweets": 10,
      "created_utc": 1779457545,
      "permalink": "https://x.com/ElectionDigest/status/2057820210481053896",
      "source": "twitter"
    },
    {
      "id": "x_2057819440201289957",
      "text": "RT @observinthecity: Brad Bradford on his way to literally rain on our parade. Remember this when he shows up during pride trying to pander…",
      "author": "Election Digest",
      "handle": "@ElectionDigest",
      "likes": 0,
      "retweets": 13,
      "created_utc": 1779457361,
      "permalink": "https://x.com/ElectionDigest/status/2057819440201289957",
      "source": "twitter"
    },
    {
      "id": "x_2057818398017380794",
      "text": "@drivandalism Let’s just hope that Brad Bradford loses this election and is sent to the unemployment line.",
      "author": "The Truth about Brad Bradford.",
      "handle": "@TruthBrad29269",
      "likes": 0,
      "retweets": 0,
      "created_utc": 1779457113,
      "permalink": "https://x.com/TruthBrad29269/status/2057818398017380794",
      "source": "twitter"
    },
    {
      "id": "x_2057810987974046024",
      "text": "Not long until the OFFICIAL, enacted by law,\n#InjuredWorkersDay \nOn June 1st \n\nAlso events\nTHUNDER BAY • May 29th\nCity Hall, 10am\n\nTORONTO • June 1st\nQueen's Park, 11am\n\nHAMILTON • June 1st\nCity Hall, 11am\n\nLONDON • June 1st\nNW Corner of Victoria Park, 1pm\n\nWINDSOR • June https://t.co/msQsbMHilq",
      "author": "fight wcb",
      "handle": "@fightthewcb",
      "likes": 4,
      "retweets": 4,
      "created_utc": 1779455346,
      "permalink": "https://x.com/fightthewcb/status/2057810987974046024",
      "source": "twitter"
    },
    {
      "id": "x_2057810767898984849",
      "text": "Not ling until the OFFICIAL enacted by law the\n#InjuredWorkersDay \nOn June 1st \nAlso events\nTHUNDER BAY • May 29th\nCity Hall, 10am\n\nTORONTO • June 1st\nQueen's Park, 11am\n\nHAMILTON • June 1st\nCity Hall, 11am\n\nLONDON • June 1st\nNW Corner of Victoria Park, 1pm\n\nWINDSOR • June https://t.co/m1ICug3O5S",
      "author": "fight wcb",
      "handle": "@fightthewcb",
      "likes": 0,
      "retweets": 0,
      "created_utc": 1779455293,
      "permalink": "https://x.com/fightthewcb/status/2057810767898984849",
      "source": "twitter"
    },
    {
      "id": "x_2057793716392181856",
      "text": "RT @3mpwrApp0816: 🔥 Injured Workers Day 2026\n\n• Thunder Bay: May 29, 10 AM (City Hall)\n\n• Toronto: June 1, 11 AM (Queens Park)\n\n• Hamilton:…",
      "author": "Occupy WSIB",
      "handle": "@occupywsib",
      "likes": 0,
      "retweets": 7,
      "created_utc": 1779451228,
      "permalink": "https://x.com/occupywsib/status/2057793716392181856",
      "source": "twitter"
    },
    {
      "id": "x_2057789938544882075",
      "text": "RT @JakeLandauTO: Toronto City Hall was designed for people to walk on the upper deck, but city council keeps it closed off for soooooo lon…",
      "author": "agriculture in the city",
      "handle": "@deku1_zero",
      "likes": 0,
      "retweets": 20,
      "created_utc": 1779450327,
      "permalink": "https://x.com/deku1_zero/status/2057789938544882075",
      "source": "twitter"
    },
    {
      "id": "x_2057786725565436185",
      "text": "RT @3mpwrApp0816: 🔥 Injured Workers Day 2026\n\n• Thunder Bay: May 29, 10 AM (City Hall)\n\n• Toronto: June 1, 11 AM (Queens Park)\n\n• Hamilton:…",
      "author": "linda haslett",
      "handle": "@lindahaslett",
      "likes": 0,
      "retweets": 7,
      "created_utc": 1779449561,
      "permalink": "https://x.com/lindahaslett/status/2057786725565436185",
      "source": "twitter"
    },
    {
      "id": "bsky_joshmatlow.bsky.social_3mmgrsyry322e",
      "text": "Doug Ford may think that his voice is the only one that matters. I believe that Toronto residents should be able to have a say about the future of their city’s waterfront.",
      "author": "Josh Matlow",
      "handle": "joshmatlow.bsky.social",
      "likes": 0,
      "retweets": 0,
      "created_utc": 1779447664,
      "permalink": "https://bsky.app/profile/joshmatlow.bsky.social/post/3mmgrsyry322e",
      "source": "bluesky"
    },
    {
      "id": "x_2057766987355336981",
      "text": "RT @EritreaInCanada: Tomorrow the #Eritrea|n flag shall be raised at #Toronto city hall in honour of our 35th Independence Day anniversary.…",
      "author": "Saba Asres",
      "handle": "@AsresSaba42029",
      "likes": 0,
      "retweets": 80,
      "created_utc": 1779444855,
      "permalink": "https://x.com/AsresSaba42029/status/2057766987355336981",
      "source": "twitter"
    },
    {
      "id": "x_2057759797601022322",
      "text": "RT @EritreaInCanada: Tomorrow the #Eritrea|n flag shall be raised at #Toronto city hall in honour of our 35th Independence Day anniversary.…",
      "author": "Bereket Mogos",
      "handle": "@BereketMogos4",
      "likes": 0,
      "retweets": 80,
      "created_utc": 1779443141,
      "permalink": "https://x.com/BereketMogos4/status/2057759797601022322",
      "source": "twitter"
    },
    {
      "id": "x_2057755657890402614",
      "text": "Old City Hall Toronto I Canvas Prints by The Learning Curve Photography on @amazon\n\nhttps://t.co/8AT9lvp8IN\n\n#prints #amazon #wallart #canvasprints #thelearningcurvephotography #toronto #architecture #blackandwhitephotography #originalphotography #photography https://t.co/EPxViYL3YN",
      "author": "LearningCurvePhoto",
      "handle": "@learningcurveca",
      "likes": 0,
      "retweets": 0,
      "created_utc": 1779442154,
      "permalink": "https://x.com/learningcurveca/status/2057755657890402614",
      "source": "twitter"
    },
    {
      "id": "x_2057753915739840727",
      "text": "RT @S_Igbu: Seeing the Eritrean flag raised at Toronto City Hall never gets old. 🇪🇷\nA flag that carries sacrifice, resilience, and identity…",
      "author": "Mengsteab",
      "handle": "@qeyih_bahri",
      "likes": 0,
      "retweets": 108,
      "created_utc": 1779441739,
      "permalink": "https://x.com/qeyih_bahri/status/2057753915739840727",
      "source": "twitter"
    },
    {
      "id": "x_2057751323857089014",
      "text": "RT @EritreaInCanada: Tomorrow the #Eritrea|n flag shall be raised at #Toronto city hall in honour of our 35th Independence Day anniversary.…",
      "author": "samri",
      "handle": "@TekleSemira",
      "likes": 0,
      "retweets": 80,
      "created_utc": 1779441121,
      "permalink": "https://x.com/TekleSemira/status/2057751323857089014",
      "source": "twitter"
    },
    {
      "id": "x_2057747617493164163",
      "text": "RT @S_Igbu: Seeing the Eritrean flag raised at Toronto City Hall never gets old. 🇪🇷\nA flag that carries sacrifice, resilience, and identity…",
      "author": "Brkti Rezene",
      "handle": "@BrktiRezene",
      "likes": 0,
      "retweets": 108,
      "created_utc": 1779440237,
      "permalink": "https://x.com/BrktiRezene/status/2057747617493164163",
      "source": "twitter"
    },
    {
      "id": "x_2057696324607209677",
      "text": "RT @db_maggi: @imPatrickT The Cinesphere at Ontario Place in Toronto, was the world’s first permanent IMAX cinema until City Hall and Doug…",
      "author": "I like basically everyone, but mostly EXO’s KAI",
      "handle": "@oreostansstuff",
      "likes": 0,
      "retweets": 2,
      "created_utc": 1779428008,
      "permalink": "https://x.com/oreostansstuff/status/2057696324607209677",
      "source": "twitter"
    },
    {
      "id": "x_2057668415180112206",
      "text": "Imagine thinking a local council referendum will stop Doug Ford from turning Billy Bishop into a massive jet hub. City hall is begging for a ballot vote while Queen's Park is literally rewriting the law to seize the land. Grab the popcorn. #TOpoli #BillyBishop #Toronto #onpoli",
      "author": "Goodness And Mercy",
      "handle": "@FineAndRich",
      "likes": 0,
      "retweets": 0,
      "created_utc": 1779421354,
      "permalink": "https://x.com/FineAndRich/status/2057668415180112206",
      "source": "twitter"
    },
    {
      "id": "x_2057663524097159531",
      "text": "RT @EritreaInCanada: Tomorrow the #Eritrea|n flag shall be raised at #Toronto city hall in honour of our 35th Independence Day anniversary.…",
      "author": "Asterb15",
      "handle": "@Asterb15",
      "likes": 0,
      "retweets": 80,
      "created_utc": 1779420188,
      "permalink": "https://x.com/Asterb15/status/2057663524097159531",
      "source": "twitter"
    },
    {
      "id": "x_2057661573888344420",
      "text": "RT @JakeLandauTO: Toronto City Hall was designed for people to walk on the upper deck, but city council keeps it closed off for soooooo lon…",
      "author": "john hartley",
      "handle": "@johnnybeegoode2",
      "likes": 0,
      "retweets": 20,
      "created_utc": 1779419723,
      "permalink": "https://x.com/johnnybeegoode2/status/2057661573888344420",
      "source": "twitter"
    },
    {
      "id": "x_2057659820430201043",
      "text": "RT @S_Igbu: Seeing the Eritrean flag raised at Toronto City Hall never gets old. 🇪🇷\nA flag that carries sacrifice, resilience, and identity…",
      "author": "Asterb15",
      "handle": "@Asterb15",
      "likes": 0,
      "retweets": 108,
      "created_utc": 1779419305,
      "permalink": "https://x.com/Asterb15/status/2057659820430201043",
      "source": "twitter"
    },
    {
      "id": "x_2057657316426608744",
      "text": "Eritrean 🇪🇷35th Independence Day flag raising ceremony at city hall in Toronto,  Canada 🇨🇦. https://t.co/kirTJ0SyWZ",
      "author": "Eritreana",
      "handle": "@EritreanaTsion",
      "likes": 0,
      "retweets": 0,
      "created_utc": 1779418708,
      "permalink": "https://x.com/EritreanaTsion/status/2057657316426608744",
      "source": "twitter"
    },
    {
      "id": "x_2057638615950197160",
      "text": "I should make an electoral model of Ottawa's municipal election and then NOT make one for Toronto for the #lolz",
      "author": "Canada Projections🇨🇦",
      "handle": "@CDNprojections",
      "likes": 17,
      "retweets": 0,
      "created_utc": 1779414249,
      "permalink": "https://x.com/CDNprojections/status/2057638615950197160",
      "source": "twitter"
    },
    {
      "id": "x_2057518864859308330",
      "text": "RT @GSawision: When you go vote in next Toronto municipal election,think about what happened in the USA same machines,same hack https://t.c…",
      "author": "Just_My_Opinion",
      "handle": "@Pick_A_Lane",
      "likes": 0,
      "retweets": 2,
      "created_utc": 1779385698,
      "permalink": "https://x.com/Pick_A_Lane/status/2057518864859308330",
      "source": "twitter"
    },
    {
      "id": "x_2057509474366071209",
      "text": "When you go vote in next Toronto municipal election,think about what happened in the USA same machines,same hack https://t.co/7b2jzZLk0e",
      "author": "George Sawision ME",
      "handle": "@GSawision",
      "likes": 1,
      "retweets": 2,
      "created_utc": 1779383460,
      "permalink": "https://x.com/GSawision/status/2057509474366071209",
      "source": "twitter"
    },
    {
      "id": "x_2057442532208807991",
      "text": "Oops I have been muted by the anonymous NDP activist ,this is a typical reaction as the truth about a candidate comes out. NDP protects their politicians ,this Toronto municipal election is a farce and don't think local media doesn't play a big part in the corruption and https://t.co/CD2DWxMto8",
      "author": "George Sawision ME",
      "handle": "@GSawision",
      "likes": 2,
      "retweets": 0,
      "created_utc": 1779367499,
      "permalink": "https://x.com/GSawision/status/2057442532208807991",
      "source": "twitter"
    },
    {
      "id": "x_2057084135009616319",
      "text": "Toronto municipal election: Oct 26, 2026 🗳️ Free tools to help you vote informed:\n\n🏙️ https://t.co/k2lL4xLDgJ ➡️ councillor votes + City Hall alerts\n👥 https://t.co/1azAyWvWT8 ➡️ voting history &amp; profiles\n\nCheck https://t.co/X8N8mQaoNs. All free. All open data. RT for your ward https://t.co/p9eKGrezoK",
      "author": "Open Data - Toronto",
      "handle": "@Open_TO",
      "likes": 2,
      "retweets": 1,
      "created_utc": 1779282051,
      "permalink": "https://x.com/Open_TO/status/2057084135009616319",
      "source": "twitter"
    },
    {
      "id": "x_2056797124164035055",
      "text": "If a person, corporation or trade union plans to spend money to promote, support or oppose a candidate in the 2026 Toronto municipal election, they must register as a third-party advertiser. \n\nFor more information, visit: https://t.co/JVdCVoo1nu",
      "author": "City of Toronto 🇨🇦",
      "handle": "@cityoftoronto",
      "likes": 14,
      "retweets": 3,
      "created_utc": 1779213622,
      "permalink": "https://x.com/cityoftoronto/status/2056797124164035055",
      "source": "twitter"
    },
    {
      "id": "x_2056706446599795006",
      "text": "CBC Toronto includes expert insight from political science professor Zack Taylor about political advocacy groups in Toronto running attack ads ahead of the upcoming municipal election. Read more:\nhttps://t.co/JIRGvvRDIF",
      "author": "Social Sci @WesternU",
      "handle": "@westernuSocSci",
      "likes": 1,
      "retweets": 0,
      "created_utc": 1779192003,
      "permalink": "https://x.com/westernuSocSci/status/2056706446599795006",
      "source": "twitter"
    },
    {
      "id": "x_2055974468900487234",
      "text": "Stephen Lecce actively campaigned for and endorsed former Toronto Sun columnist Anthony Furey far-right canidate who was defeated during the November 2024 municipal by-election for Don Valley West. https://t.co/N96fYCbGS3 https://t.co/CxzKRIxvOr",
      "author": "P.b.Freire",
      "handle": "@Freire1Pb",
      "likes": 2,
      "retweets": 2,
      "created_utc": 1779017486,
      "permalink": "https://x.com/Freire1Pb/status/2055974468900487234",
      "source": "twitter"
    },
    {
      "id": "x_2055699953981260159",
      "text": "Why aren’t municipal candidates talking about police scandals and corruption, asks @TorontoStar columnist @shawnmicallef #Toronto #policing #election https://t.co/XdbPGo7gj3",
      "author": "Stephen Tustin",
      "handle": "@stustin",
      "likes": 24,
      "retweets": 13,
      "created_utc": 1778952036,
      "permalink": "https://x.com/stustin/status/2055699953981260159",
      "source": "twitter"
    },
    {
      "id": "bsky_joshmatlow.bsky.social_3mlp2vo7h6k2i",
      "text": "Waterfront for All invited me to address their speaker series where I discussed why we must fight back hard, and fight for a beautiful, livable and vibrant Toronto waterfront that is so much more than just a runway for jets. Please make your voice heard: www.joshmatlow.ca/waterfront",
      "author": "Josh Matlow",
      "handle": "joshmatlow.bsky.social",
      "likes": 0,
      "retweets": 0,
      "created_utc": 1778632783,
      "permalink": "https://bsky.app/profile/joshmatlow.bsky.social/post/3mlp2vo7h6k2i",
      "source": "bluesky"
    },
    {
      "id": "bsky_joshmatlow.bsky.social_3mloyrk7mq22i",
      "text": "Waterfront for All invited me to address their speaker series where I discussed why we must fight back hard, and fight for a beautiful, livable and vibrant Toronto waterfront that is so much more than just a runway for jets.",
      "author": "Josh Matlow",
      "handle": "joshmatlow.bsky.social",
      "likes": 0,
      "retweets": 0,
      "created_utc": 1778630497,
      "permalink": "https://bsky.app/profile/joshmatlow.bsky.social/post/3mloyrk7mq22i",
      "source": "bluesky"
    },
    {
      "id": "bsky_joshmatlow.bsky.social_3mlc7ikfpx224",
      "text": "Doug Ford made an announcement, but we have a plan. We have a Made-in-Toronto plan for our city’s waterfront - including a vibrant new neighbourhood in the Port Lands, affordable homes, several new remarkable parks and year-round vision for…",
      "author": "Josh Matlow",
      "handle": "joshmatlow.bsky.social",
      "likes": 0,
      "retweets": 0,
      "created_utc": 1778191035,
      "permalink": "https://bsky.app/profile/joshmatlow.bsky.social/post/3mlc7ikfpx224",
      "source": "bluesky"
    },
    {
      "id": "bsky_joshmatlow.bsky.social_3mkxv6sr3ts2i",
      "text": "Thank you to my friends in our city and region’s Sikh community for inviting me to the Khalsa Day parade in Etobicoke today! Waheguru Ji Ka Khalsa, Waheguru Ji Ki Fateh.",
      "author": "Josh Matlow",
      "handle": "joshmatlow.bsky.social",
      "likes": 0,
      "retweets": 0,
      "created_utc": 1777836374,
      "permalink": "https://bsky.app/profile/joshmatlow.bsky.social/post/3mkxv6sr3ts2i",
      "source": "bluesky"
    },
    {
      "id": "bsky_coteau.bsky.social_3ln3w22xmes23",
      "text": "Advance polls are now open in Scarborough–Woburn! From today through Monday, you can cast your vote early.",
      "author": "Michael Coteau",
      "handle": "coteau.bsky.social",
      "likes": 0,
      "retweets": 0,
      "created_utc": 1744989378,
      "permalink": "https://bsky.app/profile/coteau.bsky.social/post/3ln3w22xmes23",
      "source": "bluesky"
    },
    {
      "id": "bsky_coteau.bsky.social_3lhya4kruss27",
      "text": "Went out canvassing for Andrea Hazell in Scarborough-Guildwood! She’s got a fantastic team working hard to connect with voters. If you can, come out and help—every conversation counts! #TeamHazel #ScarboroughGuildwood #OnPoli @AndreaHazelll",
      "author": "Michael Coteau",
      "handle": "coteau.bsky.social",
      "likes": 0,
      "retweets": 0,
      "created_utc": 1739365202,
      "permalink": "https://bsky.app/profile/coteau.bsky.social/post/3lhya4kruss27",
      "source": "bluesky"
    },
    {
      "id": "bsky_coteau.bsky.social_3lhrapglt5222",
      "text": "Happy to support @QadiraJackson as she runs to be the next MPP for Scarborough Southwest! Her passion, dedication, and commitment to the community are exactly what’s needed at Queen’s Park. Honoured to speak at her fundraiser—let’s get her elected! #onpoli #TeamQadira",
      "author": "Michael Coteau",
      "handle": "coteau.bsky.social",
      "likes": 0,
      "retweets": 0,
      "created_utc": 1739125317,
      "permalink": "https://bsky.app/profile/coteau.bsky.social/post/3lhrapglt5222",
      "source": "bluesky"
    },
    {
      "id": "bsky_coteau.bsky.social_3lhqynqlbb226",
      "text": "Great to join Andrea Hazell in Scarborough-Guildwood as she runs for re-election as MPP! Andrea brings the kind of energy needed at Queen’s Park to amplify the voices and concerns of her constituents. Looking forward to seeing her continue to deliver for the community! #onpoli @AndreaHazelll",
      "author": "Michael Coteau",
      "handle": "coteau.bsky.social",
      "likes": 0,
      "retweets": 0,
      "created_utc": 1739116671,
      "permalink": "https://bsky.app/profile/coteau.bsky.social/post/3lhqynqlbb226",
      "source": "bluesky"
    },
    {
      "id": "bsky_coteau.bsky.social_3lhlq2hjjgc2s",
      "text": "Great attending the Toronto Educational Opportunity Fund Lunar New Year event to help raise money for student nutrition programs. Thank you, Toronto Education Workers/Local 4400, for your dedication to students. Always great seeing everyone! #StudentNutrition #TOpoli",
      "author": "Michael Coteau",
      "handle": "coteau.bsky.social",
      "likes": 0,
      "retweets": 0,
      "created_utc": 1738935635,
      "permalink": "https://bsky.app/profile/coteau.bsky.social/post/3lhlq2hjjgc2s",
      "source": "bluesky"
    },
    {
      "id": "bsky_coteau.bsky.social_3lcyskaglas2k",
      "text": "Mike Harris’s cuts to social services, housing, and healthcare pushed Ontario’s most vulnerable deeper into crisis. Pierre Poilievre is singing the same tune: tax cuts for the rich, austerity for the rest. We can’t afford another era of cruel, short-sighted policies. #cdnpoli",
      "author": "Michael Coteau",
      "handle": "coteau.bsky.social",
      "likes": 0,
      "retweets": 0,
      "created_utc": 1733887430,
      "permalink": "https://bsky.app/profile/coteau.bsky.social/post/3lcyskaglas2k",
      "source": "bluesky"
    },
    {
      "id": "bsky_coteau.bsky.social_3lcysjumtec2k",
      "text": "Pierre Poilievre’s playbook feels eerily familiar: tax cuts for the wealthy, slashing public services, and a ‘common sense’ branding. Looks like he’s channeling Mike Harris’s divisive and damaging legacy. We’ve seen this movie before, and we know how it ends. #cdnpoli",
      "author": "Michael Coteau",
      "handle": "coteau.bsky.social",
      "likes": 0,
      "retweets": 0,
      "created_utc": 1733887418,
      "permalink": "https://bsky.app/profile/coteau.bsky.social/post/3lcysjumtec2k",
      "source": "bluesky"
    }
  ],
  "sentiment": {
    "chowSentiment": {
      "positive": 0,
      "negative": 0,
      "neutral": 20,
      "total": 20,
      "score": 0,
      "trend": "up"
    },
    "bradfordSentiment": {
      "positive": 0,
      "negative": 0,
      "neutral": 20,
      "total": 20,
      "score": 0,
      "trend": "up"
    },
    "topIssues": [
      {
        "name": "Housing",
        "count": 3,
        "sentiment": 0
      },
      {
        "name": "Affordability",
        "count": 1,
        "sentiment": 0
      },
      {
        "name": "Transit/TTC",
        "count": 1,
        "sentiment": 0
      },
      {
        "name": "Homelessness",
        "count": 1,
        "sentiment": 0
      },
      {
        "name": "Safety",
        "count": 1,
        "sentiment": 0
      },
      {
        "name": "Development",
        "count": 1,
        "sentiment": 0
      }
    ],
    "volumeByDay": [
      {
        "date": "2026-05-09",
        "chowPos": 0,
        "chowNeg": 0,
        "chowNeutral": 0,
        "bradPos": 0,
        "bradNeg": 0,
        "bradNeutral": 0,
        "total": 0
      },
      {
        "date": "2026-05-10",
        "chowPos": 0,
        "chowNeg": 0,
        "chowNeutral": 0,
        "bradPos": 0,
        "bradNeg": 0,
        "bradNeutral": 0,
        "total": 0
      },
      {
        "date": "2026-05-11",
        "chowPos": 0,
        "chowNeg": 0,
        "chowNeutral": 0,
        "bradPos": 0,
        "bradNeg": 0,
        "bradNeutral": 0,
        "total": 0
      },
      {
        "date": "2026-05-12",
        "chowPos": 0,
        "chowNeg": 0,
        "chowNeutral": 0,
        "bradPos": 0,
        "bradNeg": 0,
        "bradNeutral": 0,
        "total": 0
      },
      {
        "date": "2026-05-13",
        "chowPos": 0,
        "chowNeg": 0,
        "chowNeutral": 0,
        "bradPos": 0,
        "bradNeg": 0,
        "bradNeutral": 0,
        "total": 0
      },
      {
        "date": "2026-05-14",
        "chowPos": 0,
        "chowNeg": 0,
        "chowNeutral": 0,
        "bradPos": 0,
        "bradNeg": 0,
        "bradNeutral": 0,
        "total": 0
      },
      {
        "date": "2026-05-15",
        "chowPos": 0,
        "chowNeg": 0,
        "chowNeutral": 0,
        "bradPos": 0,
        "bradNeg": 0,
        "bradNeutral": 0,
        "total": 0
      },
      {
        "date": "2026-05-16",
        "chowPos": 0,
        "chowNeg": 0,
        "chowNeutral": 0,
        "bradPos": 0,
        "bradNeg": 0,
        "bradNeutral": 0,
        "total": 0
      },
      {
        "date": "2026-05-17",
        "chowPos": 0,
        "chowNeg": 0,
        "chowNeutral": 0,
        "bradPos": 0,
        "bradNeg": 0,
        "bradNeutral": 0,
        "total": 0
      },
      {
        "date": "2026-05-18",
        "chowPos": 0,
        "chowNeg": 0,
        "chowNeutral": 0,
        "bradPos": 0,
        "bradNeg": 0,
        "bradNeutral": 0,
        "total": 0
      },
      {
        "date": "2026-05-19",
        "chowPos": 0,
        "chowNeg": 0,
        "chowNeutral": 0,
        "bradPos": 0,
        "bradNeg": 0,
        "bradNeutral": 0,
        "total": 0
      },
      {
        "date": "2026-05-20",
        "chowPos": 0,
        "chowNeg": 0,
        "chowNeutral": 0,
        "bradPos": 0,
        "bradNeg": 0,
        "bradNeutral": 0,
        "total": 0
      },
      {
        "date": "2026-05-21",
        "chowPos": 0,
        "chowNeg": 0,
        "chowNeutral": 0,
        "bradPos": 0,
        "bradNeg": 0,
        "bradNeutral": 0,
        "total": 0
      },
      {
        "date": "2026-05-22",
        "chowPos": 0,
        "chowNeg": 0,
        "chowNeutral": 20,
        "bradPos": 0,
        "bradNeg": 0,
        "bradNeutral": 20,
        "total": 40
      }
    ],
    "geoData": [
      {
        "area": "Scarborough",
        "count": 4,
        "sentiment": 0
      },
      {
        "area": "Etobicoke",
        "count": 1,
        "sentiment": 0
      }
    ],
    "postsAnalyzed": 91,
    "lastUpdated": 1779464976509
  }
}